pycomfort/__init__.py
pycomfort/comfort.py
pycomfort/config.py
pycomfort/files.py
pycomfort/logging.py
pycomfort-0.0.18.dist-info/LICENSE
pycomfort-0.0.18.dist-info/METADATA
pycomfort-0.0.18.dist-info/WHEEL
pycomfort-0.0.18.dist-info/entry_points.txt
pycomfort-0.0.18.dist-info/RECORD
