Metadata-Version: 2.3
Name: pycomfort
Version: 0.0.18
Summary: Python helper methods to make life easier
License: Apache-2.0
Keywords: python,utils,files
Author: Anton Kulaga
Author-email: antonkulaga@gmail.com
Requires-Python: >=3.10,<3.15
Classifier: Development Status :: 2 - Pre-Alpha
Classifier: Intended Audience :: Developers
Classifier: License :: OSI Approved :: Apache Software License
Classifier: Operating System :: MacOS :: MacOS X
Classifier: Operating System :: Microsoft :: Windows
Classifier: Operating System :: Unix
Classifier: Programming Language :: Python :: 3
Classifier: Programming Language :: Python :: 3.10
Classifier: Programming Language :: Python :: 3.11
Classifier: Programming Language :: Python :: 3.12
Classifier: Programming Language :: Python :: 3.13
Requires-Dist: Deprecated (>=1.2.15)
Requires-Dist: eliot (>=1.17.5)
Requires-Dist: eliot-tree (>=24.0.0)
Requires-Dist: more-itertools (>=10.6.0)
Requires-Dist: pyfunctional (<=1.5.0)
Requires-Dist: python-dotenv
Requires-Dist: typer (>=0.15.2)
Project-URL: Homepage, https://github.com/antonkulaga/pycomfort
Project-URL: Repository, https://github.com/antonkulaga/pycomfort
